Metadata-Version: 2.1
Name: babygruut
Version: 2.3.4
Summary: A tokenizer, text cleaner, and phonemizer for many human languages.
Home-page: https://github.com/bookbot-hive/babygruut
Classifier: Programming Language :: Python :: 3
Classifier: Programming Language :: Python :: 3.6
Classifier: Programming Language :: Python :: 3.7
Classifier: Programming Language :: Python :: 3.8
Classifier: Programming Language :: Python :: 3.9
Classifier: License :: OSI Approved :: MIT License
Requires-Python: >=3.6
License-File: LICENSE
Requires-Dist: Babel (<3.0.0,>=2.8.0)
Requires-Dist: dateparser (~=1.1.0)
Requires-Dist: gruut-ipa (<1.0,>=0.12.0)
Requires-Dist: babygruut-lang-en
Requires-Dist: jsonlines (~=1.2.0)
Requires-Dist: networkx (<3.0.0,>=2.5.0)
Requires-Dist: num2words (<1.0.0,>=0.5.10)
Requires-Dist: numpy (<2.0.0,>=1.19.0)
Requires-Dist: python-crfsuite (~=0.9.7)
Requires-Dist: dataclasses ; python_version<"3.7"
Requires-Dist: types-dataclasses ; python_version<"3.7"
Requires-Dist: importlib-resources ; python_version<"3.9"
Provides-Extra: align
Requires-Dist: aeneas (~=1.7.3.0) ; extra == 'align'
Requires-Dist: pydub (~=0.24.1) ; extra == 'align'
Provides-Extra: all
Requires-Dist: hazm (~=0.7.0) ; extra == 'all'
Requires-Dist: conllu (>=4.4) ; extra == 'all'
Requires-Dist: rapidfuzz (>=2.11.1) ; extra == 'all'
Requires-Dist: aeneas (~=1.7.3.0) ; extra == 'all'
Requires-Dist: pydub (~=0.24.1) ; extra == 'all'
Requires-Dist: mishkal (~=0.4.0) ; extra == 'all'
Requires-Dist: codernitydb3 (~=0.6.0) ; extra == 'all'
Requires-Dist: phonetisaurus (~=0.3.0) ; extra == 'all'
Requires-Dist: gruut-lang-ar (~=2.0.0) ; extra == 'all'
Requires-Dist: gruut-lang-cs (~=2.0.0) ; extra == 'all'
Requires-Dist: gruut-lang-de (~=2.0.0) ; extra == 'all'
Requires-Dist: gruut-lang-es (~=2.0.0) ; extra == 'all'
Requires-Dist: gruut-lang-fa (~=2.0.0) ; extra == 'all'
Requires-Dist: gruut-lang-fr (~=2.0.0) ; extra == 'all'
Requires-Dist: gruut-lang-it (~=2.0.0) ; extra == 'all'
Requires-Dist: gruut-lang-lb (~=2.0.0) ; extra == 'all'
Requires-Dist: gruut-lang-nl (~=2.0.0) ; extra == 'all'
Requires-Dist: gruut-lang-pt (~=2.0.0) ; extra == 'all'
Requires-Dist: gruut-lang-ru (~=2.0.0) ; extra == 'all'
Requires-Dist: gruut-lang-sv (~=2.0.0) ; extra == 'all'
Requires-Dist: gruut-lang-sw (~=2.0.0) ; extra == 'all'
Provides-Extra: ar
Requires-Dist: mishkal (~=0.4.0) ; extra == 'ar'
Requires-Dist: codernitydb3 (~=0.6.0) ; extra == 'ar'
Requires-Dist: gruut-lang-ar (~=2.0.0) ; extra == 'ar'
Provides-Extra: cs
Requires-Dist: gruut-lang-cs (~=2.0.0) ; extra == 'cs'
Provides-Extra: de
Requires-Dist: gruut-lang-de (~=2.0.0) ; extra == 'de'
Provides-Extra: es
Requires-Dist: gruut-lang-es (~=2.0.0) ; extra == 'es'
Provides-Extra: fa
Requires-Dist: hazm (~=0.7.0) ; extra == 'fa'
Requires-Dist: gruut-lang-fa (~=2.0.0) ; extra == 'fa'
Provides-Extra: fr
Requires-Dist: gruut-lang-fr (~=2.0.0) ; extra == 'fr'
Provides-Extra: g2p
Requires-Dist: phonetisaurus (~=0.3.0) ; extra == 'g2p'
Provides-Extra: it
Requires-Dist: gruut-lang-it (~=2.0.0) ; extra == 'it'
Provides-Extra: lb
Requires-Dist: gruut-lang-lb (~=2.0.0) ; extra == 'lb'
Provides-Extra: nl
Requires-Dist: gruut-lang-nl (~=2.0.0) ; extra == 'nl'
Provides-Extra: pt
Requires-Dist: gruut-lang-pt (~=2.0.0) ; extra == 'pt'
Provides-Extra: ru
Requires-Dist: gruut-lang-ru (~=2.0.0) ; extra == 'ru'
Provides-Extra: sv
Requires-Dist: gruut-lang-sv (~=2.0.0) ; extra == 'sv'
Provides-Extra: sw
Requires-Dist: gruut-lang-sw (~=2.0.0) ; extra == 'sw'
Provides-Extra: train
Requires-Dist: conllu (>=4.4) ; extra == 'train'
Requires-Dist: rapidfuzz (>=2.11.1) ; extra == 'train'
